{
  "juzAmma": [
    {
      "number": 78,
      "nameArabic": "النبإ",
      "nameTransliteration": "An-Naba'",
      "nameTranslation": "The Tidings",
      "ayahCount": 40,
      "revelation": "Makkah",
      "ayahs": [
        {
          "number": 1,
          "textArabic": " عَمَّ يَتَسَآءَلُونَ"
        },
        {
          "number": 2,
          "textArabic": "عَنِ ٱلنَّبَإِ ٱلْعَظِيمِ"
        },
        {
          "number": 3,
          "textArabic": "ٱلَّذِى هُمْ فِيهِ مُخْتَلِفُونَ"
        },
        {
          "number": 4,
          "textArabic": "كَلَّا سَيَعْلَمُونَ"
        },
        {
          "number": 5,
          "textArabic": "ثُمَّ كَلَّا سَيَعْلَمُونَ"
        },
        {
          "number": 6,
          "textArabic": "أَلَمْ نَجْعَلِ ٱلْأَرْضَ مِهَـٰدًا"
        },
        {
          "number": 7,
          "textArabic": "وَٱلْجِبَالَ أَوْتَادًا"
        },
        {
          "number": 8,
          "textArabic": "وَخَلَقْنَـٰكُمْ أَزْوَٰجًا"
        },
        {
          "number": 9,
          "textArabic": "وَجَعَلْنَا نَوْمَكُمْ سُبَاتًا"
        },
        {
          "number": 10,
          "textArabic": "وَجَعَلْنَا ٱلَّيْلَ لِبَاسًا"
        },
        {
          "number": 11,
          "textArabic": "وَجَعَلْنَا ٱلنَّهَارَ مَعَاشًا"
        },
        {
          "number": 12,
          "textArabic": "وَبَنَيْنَا فَوْقَكُمْ سَبْعًا شِدَادًا"
        },
        {
          "number": 13,
          "textArabic": "وَجَعَلْنَا سِرَاجًا وَهَّاجًا"
        },
        {
          "number": 14,
          "textArabic": "وَأَنزَلْنَا مِنَ ٱلْمُعْصِرَٰتِ مَآءً ثَجَّاجًا"
        },
        {
          "number": 15,
          "textArabic": "لِّنُخْرِجَ بِهِۦ حَبًّا وَنَبَاتًا"
        },
        {
          "number": 16,
          "textArabic": "وَجَنَّـٰتٍ أَلْفَافًا"
        },
        {
          "number": 17,
          "textArabic": "إِنَّ يَوْمَ ٱلْفَصْلِ كَانَ مِيقَـٰتًا"
        },
        {
          "number": 18,
          "textArabic": "يَوْمَ يُنفَخُ فِى ٱلصُّورِ فَتَأْتُونَ أَفْوَاجًا"
        },
        {
          "number": 19,
          "textArabic": "وَفُتِحَتِ ٱلسَّمَآءُ فَكَانَتْ أَبْوَٰبًا"
        },
        {
          "number": 20,
          "textArabic": "وَسُيِّرَتِ ٱلْجِبَالُ فَكَانَتْ سَرَابًا"
        },
        {
          "number": 21,
          "textArabic": "إِنَّ جَهَنَّمَ كَانَتْ مِرْصَادًا"
        },
        {
          "number": 22,
          "textArabic": "لِّلطَّـٰغِينَ مَـَٔابًا"
        },
        {
          "number": 23,
          "textArabic": "لَّـٰبِثِينَ فِيهَآ أَحْقَابًا"
        },
        {
          "number": 24,
          "textArabic": "لَّا يَذُوقُونَ فِيهَا بَرْدًا وَلَا شَرَابًا"
        },
        {
          "number": 25,
          "textArabic": "إِلَّا حَمِيمًا وَغَسَّاقًا"
        },
        {
          "number": 26,
          "textArabic": "جَزَآءً وِفَاقًا"
        },
        {
          "number": 27,
          "textArabic": "إِنَّهُمْ كَانُوا۟ لَا يَرْجُونَ حِسَابًا"
        },
        {
          "number": 28,
          "textArabic": "وَكَذَّبُوا۟ بِـَٔايَـٰتِنَا كِذَّابًا"
        },
        {
          "number": 29,
          "textArabic": "وَكُلَّ شَىْءٍ أَحْصَيْنَـٰهُ كِتَـٰبًا"
        },
        {
          "number": 30,
          "textArabic": "فَذُوقُوا۟ فَلَن نَّزِيدَكُمْ إِلَّا عَذَابًا"
        },
        {
          "number": 31,
          "textArabic": "إِنَّ لِلْمُتَّقِينَ مَفَازًا"
        },
        {
          "number": 32,
          "textArabic": "حَدَآئِقَ وَأَعْنَـٰبًا"
        },
        {
          "number": 33,
          "textArabic": "وَكَوَاعِبَ أَتْرَابًا"
        },
        {
          "number": 34,
          "textArabic": "وَكَأْسًا دِهَاقًا"
        },
        {
          "number": 35,
          "textArabic": "لَّا يَسْمَعُونَ فِيهَا لَغْوًا وَلَا كِذَّٰبًا"
        },
        {
          "number": 36,
          "textArabic": "جَزَآءً مِّن رَّبِّكَ عَطَآءً حِسَابًا"
        },
        {
          "number": 37,
          "textArabic": "رَّبِّ ٱلسَّمَـٰوَٰتِ وَٱلْأَرْضِ وَمَا بَيْنَهُمَا ٱلرَّحْمَـٰنِ ۖ لَا يَمْلِكُونَ مِنْهُ خِطَابًا"
        },
        {
          "number": 38,
          "textArabic": "يَوْمَ يَقُومُ ٱلرُّوحُ وَٱلْمَلَـٰٓئِكَةُ صَفًّا ۖ لَّا يَتَكَلَّمُونَ إِلَّا مَنْ أَذِنَ لَهُ ٱلرَّحْمَـٰنُ وَقَالَ صَوَابًا"
        },
        {
          "number": 39,
          "textArabic": "ذَٰلِكَ ٱلْيَوْمُ ٱلْحَقُّ ۖ فَمَن شَآءَ ٱتَّخَذَ إِلَىٰ رَبِّهِۦ مَـَٔابًا"
        },
        {
          "number": 40,
          "textArabic": "إِنَّآ أَنذَرْنَـٰكُمْ عَذَابًا قَرِيبًا يَوْمَ يَنظُرُ ٱلْمَرْءُ مَا قَدَّمَتْ يَدَاهُ وَيَقُولُ ٱلْكَافِرُ يَـٰلَيْتَنِى كُنتُ تُرَٰبًۢا"
        }
      ]
    },
    {
      "number": 79,
      "nameArabic": "النازعات",
      "nameTransliteration": "An-Nazi'at",
      "nameTranslation": "Those Who Pull Out",
      "ayahCount": 46,
      "revelation": "Makkah",
      "ayahs": [
        {
          "number": 1,
          "textArabic": " وَٱلنَّـٰزِعَـٰتِ غَرْقًا"
        },
        {
          "number": 2,
          "textArabic": "وَٱلنَّـٰشِطَـٰتِ نَشْطًا"
        },
        {
          "number": 3,
          "textArabic": "وَٱلسَّـٰبِحَـٰتِ سَبْحًا"
        },
        {
          "number": 4,
          "textArabic": "فَٱلسَّـٰبِقَـٰتِ سَبْقًا"
        },
        {
          "number": 5,
          "textArabic": "فَٱلْمُدَبِّرَٰتِ أَمْرًا"
        },
        {
          "number": 6,
          "textArabic": "يَوْمَ تَرْجُفُ ٱلرَّاجِفَةُ"
        },
        {
          "number": 7,
          "textArabic": "تَتْبَعُهَا ٱلرَّادِفَةُ"
        },
        {
          "number": 8,
          "textArabic": "قُلُوبٌ يَوْمَئِذٍ وَاجِفَةٌ"
        },
        {
          "number": 9,
          "textArabic": "أَبْصَـٰرُهَا خَـٰشِعَةٌ"
        },
        {
          "number": 10,
          "textArabic": "يَقُولُونَ أَءِنَّا لَمَرْدُودُونَ فِى ٱلْحَافِرَةِ"
        },
        {
          "number": 11,
          "textArabic": "أَءِذَا كُنَّا عِظَـٰمًا نَّخِرَةً"
        },
        {
          "number": 12,
          "textArabic": "قَالُوا۟ تِلْكَ إِذًا كَرَّةٌ خَاسِرَةٌ"
        },
        {
          "number": 13,
          "textArabic": "فَإِنَّمَا هِىَ زَجْرَةٌ وَٰحِدَةٌ"
        },
        {
          "number": 14,
          "textArabic": "فَإِذَا هُم بِٱلسَّاهِرَةِ"
        },
        {
          "number": 15,
          "textArabic": "هَلْ أَتَىٰكَ حَدِيثُ مُوسَىٰٓ"
        },
        {
          "number": 16,
          "textArabic": "إِذْ نَادَىٰهُ رَبُّهُۥ بِٱلْوَادِ ٱلْمُقَدَّسِ طُوًى"
        },
        {
          "number": 17,
          "textArabic": "ٱذْهَبْ إِلَىٰ فِرْعَوْنَ إِنَّهُۥ طَغَىٰ"
        },
        {
          "number": 18,
          "textArabic": "فَقُلْ هَل لَّكَ إِلَىٰٓ أَن تَزَكَّىٰ"
        },
        {
          "number": 19,
          "textArabic": "وَأَهْدِيَكَ إِلَىٰ رَبِّكَ فَتَخْشَىٰ"
        },
        {
          "number": 20,
          "textArabic": "فَأَرَىٰهُ ٱلْـَٔايَةَ ٱلْكُبْرَىٰ"
        },
        {
          "number": 21,
          "textArabic": "فَكَذَّبَ وَعَصَىٰ"
        },
        {
          "number": 22,
          "textArabic": "ثُمَّ أَدْبَرَ يَسْعَىٰ"
        },
        {
          "number": 23,
          "textArabic": "فَحَشَرَ فَنَادَىٰ"
        },
        {
          "number": 24,
          "textArabic": "فَقَالَ أَنَا۠ رَبُّكُمُ ٱلْأَعْلَىٰ"
        },
        {
          "number": 25,
          "textArabic": "فَأَخَذَهُ ٱللَّهُ نَكَالَ ٱلْـَٔاخِرَةِ وَٱلْأُولَىٰٓ"
        },
        {
          "number": 26,
          "textArabic": "إِنَّ فِى ذَٰلِكَ لَعِبْرَةً لِّمَن يَخْشَىٰٓ"
        },
        {
          "number": 27,
          "textArabic": "ءَأَنتُمْ أَشَدُّ خَلْقًا أَمِ ٱلسَّمَآءُ ۚ بَنَىٰهَا"
        },
        {
          "number": 28,
          "textArabic": "رَفَعَ سَمْكَهَا فَسَوَّىٰهَا"
        },
        {
          "number": 29,
          "textArabic": "وَأَغْطَشَ لَيْلَهَا وَأَخْرَجَ ضُحَىٰهَا"
        },
        {
          "number": 30,
          "textArabic": "وَٱلْأَرْضَ بَعْدَ ذَٰلِكَ دَحَىٰهَآ"
        },
        {
          "number": 31,
          "textArabic": "أَخْرَجَ مِنْهَا مَآءَهَا وَمَرْعَىٰهَا"
        },
        {
          "number": 32,
          "textArabic": "وَٱلْجِبَالَ أَرْسَىٰهَا"
        },
        {
          "number": 33,
          "textArabic": "مَتَـٰعًا لَّكُمْ وَلِأَنْعَـٰمِكُمْ"
        },
        {
          "number": 34,
          "textArabic": "فَإِذَا جَآءَتِ ٱلطَّآمَّةُ ٱلْكُبْرَىٰ"
        },
        {
          "number": 35,
          "textArabic": "يَوْمَ يَتَذَكَّرُ ٱلْإِنسَـٰنُ مَا سَعَىٰ"
        },
        {
          "number": 36,
          "textArabic": "وَبُرِّزَتِ ٱلْجَحِيمُ لِمَن يَرَىٰ"
        },
        {
          "number": 37,
          "textArabic": "فَأَمَّا مَن طَغَىٰ"
        },
        {
          "number": 38,
          "textArabic": "وَءَاثَرَ ٱلْحَيَوٰةَ ٱلدُّنْيَا"
        },
        {
          "number": 39,
          "textArabic": "فَإِنَّ ٱلْجَحِيمَ هِىَ ٱلْمَأْوَىٰ"
        },
        {
          "number": 40,
          "textArabic": "وَأَمَّا مَنْ خَافَ مَقَامَ رَبِّهِۦ وَنَهَى ٱلنَّفْسَ عَنِ ٱلْهَوَىٰ"
        },
        {
          "number": 41,
          "textArabic": "فَإِنَّ ٱلْجَنَّةَ هِىَ ٱلْمَأْوَىٰ"
        },
        {
          "number": 42,
          "textArabic": "يَسْـَٔلُونَكَ عَنِ ٱلسَّاعَةِ أَيَّانَ مُرْسَىٰهَا"
        },
        {
          "number": 43,
          "textArabic": "فِيمَ أَنتَ مِن ذِكْرَىٰهَآ"
        },
        {
          "number": 44,
          "textArabic": "إِلَىٰ رَبِّكَ مُنتَهَىٰهَآ"
        },
        {
          "number": 45,
          "textArabic": "إِنَّمَآ أَنتَ مُنذِرُ مَن يَخْشَىٰهَا"
        },
        {
          "number": 46,
          "textArabic": "كَأَنَّهُمْ يَوْمَ يَرَوْنَهَا لَمْ يَلْبَثُوٓا۟ إِلَّا عَشِيَّةً أَوْ ضُحَىٰهَا"
        }
      ]
    },
    {
      "number": 80,
      "nameArabic": "عبس",
      "nameTransliteration": "'Abasa",
      "nameTranslation": "He Frowned",
      "ayahCount": 42,
      "revelation": "Makkah",
      "ayahs": [
        {
          "number": 1,
          "textArabic": " عَبَسَ وَتَوَلَّىٰٓ"
        },
        {
          "number": 2,
          "textArabic": "أَن جَآءَهُ ٱلْأَعْمَىٰ"
        },
        {
          "number": 3,
          "textArabic": "وَمَا يُدْرِيكَ لَعَلَّهُۥ يَزَّكَّىٰٓ"
        },
        {
          "number": 4,
          "textArabic": "أَوْ يَذَّكَّرُ فَتَنفَعَهُ ٱلذِّكْرَىٰٓ"
        },
        {
          "number": 5,
          "textArabic": "أَمَّا مَنِ ٱسْتَغْنَىٰ"
        },
        {
          "number": 6,
          "textArabic": "فَأَنتَ لَهُۥ تَصَدَّىٰ"
        },
        {
          "number": 7,
          "textArabic": "وَمَا عَلَيْكَ أَلَّا يَزَّكَّىٰ"
        },
        {
          "number": 8,
          "textArabic": "وَأَمَّا مَن جَآءَكَ يَسْعَىٰ"
        },
        {
          "number": 9,
          "textArabic": "وَهُوَ يَخْشَىٰ"
        },
        {
          "number": 10,
          "textArabic": "فَأَنتَ عَنْهُ تَلَهَّىٰ"
        },
        {
          "number": 11,
          "textArabic": "كَلَّآ إِنَّهَا تَذْكِرَةٌ"
        },
        {
          "number": 12,
          "textArabic": "فَمَن شَآءَ ذَكَرَهُۥ"
        },
        {
          "number": 13,
          "textArabic": "فِى صُحُفٍ مُّكَرَّمَةٍ"
        },
        {
          "number": 14,
          "textArabic": "مَّرْفُوعَةٍ مُّطَهَّرَةٍۭ"
        },
        {
          "number": 15,
          "textArabic": "بِأَيْدِى سَفَرَةٍ"
        },
        {
          "number": 16,
          "textArabic": "كِرَامٍۭ بَرَرَةٍ"
        },
        {
          "number": 17,
          "textArabic": "قُتِلَ ٱلْإِنسَـٰنُ مَآ أَكْفَرَهُۥ"
        },
        {
          "number": 18,
          "textArabic": "مِنْ أَىِّ شَىْءٍ خَلَقَهُۥ"
        },
        {
          "number": 19,
          "textArabic": "مِن نُّطْفَةٍ خَلَقَهُۥ فَقَدَّرَهُۥ"
        },
        {
          "number": 20,
          "textArabic": "ثُمَّ ٱلسَّبِيلَ يَسَّرَهُۥ"
        },
        {
          "number": 21,
          "textArabic": "ثُمَّ أَمَاتَهُۥ فَأَقْبَرَهُۥ"
        },
        {
          "number": 22,
          "textArabic": "ثُمَّ إِذَا شَآءَ أَنشَرَهُۥ"
        },
        {
          "number": 23,
          "textArabic": "كَلَّا لَمَّا يَقْضِ مَآ أَمَرَهُۥ"
        },
        {
          "number": 24,
          "textArabic": "فَلْيَنظُرِ ٱلْإِنسَـٰنُ إِلَىٰ طَعَامِهِۦٓ"
        },
        {
          "number": 25,
          "textArabic": "أَنَّا صَبَبْنَا ٱلْمَآءَ صَبًّا"
        },
        {
          "number": 26,
          "textArabic": "ثُمَّ شَقَقْنَا ٱلْأَرْضَ شَقًّا"
        },
        {
          "number": 27,
          "textArabic": "فَأَنۢبَتْنَا فِيهَا حَبًّا"
        },
        {
          "number": 28,
          "textArabic": "وَعِنَبًا وَقَضْبًا"
        },
        {
          "number": 29,
          "textArabic": "وَزَيْتُونًا وَنَخْلًا"
        },
        {
          "number": 30,
          "textArabic": "وَحَدَآئِقَ غُلْبًا"
        },
        {
          "number": 31,
          "textArabic": "وَفَـٰكِهَةً وَأَبًّا"
        },
        {
          "number": 32,
          "textArabic": "مَّتَـٰعًا لَّكُمْ وَلِأَنْعَـٰمِكُمْ"
        },
        {
          "number": 33,
          "textArabic": "فَإِذَا جَآءَتِ ٱلصَّآخَّةُ"
        },
        {
          "number": 34,
          "textArabic": "يَوْمَ يَفِرُّ ٱلْمَرْءُ مِنْ أَخِيهِ"
        },
        {
          "number": 35,
          "textArabic": "وَأُمِّهِۦ وَأَبِيهِ"
        },
        {
          "number": 36,
          "textArabic": "وَصَـٰحِبَتِهِۦ وَبَنِيهِ"
        },
        {
          "number": 37,
          "textArabic": "لِكُلِّ ٱمْرِئٍ مِّنْهُمْ يَوْمَئِذٍ شَأْنٌ يُغْنِيهِ"
        },
        {
          "number": 38,
          "textArabic": "وُجُوهٌ يَوْمَئِذٍ مُّسْفِرَةٌ"
        },
        {
          "number": 39,
          "textArabic": "ضَاحِكَةٌ مُّسْتَبْشِرَةٌ"
        },
        {
          "number": 40,
          "textArabic": "وَوُجُوهٌ يَوْمَئِذٍ عَلَيْهَا غَبَرَةٌ"
        },
        {
          "number": 41,
          "textArabic": "تَرْهَقُهَا قَتَرَةٌ"
        },
        {
          "number": 42,
          "textArabic": "أُو۟لَـٰٓئِكَ هُمُ ٱلْكَفَرَةُ ٱلْفَجَرَةُ"
        }
      ]
    },
    {
      "number": 81,
      "nameArabic": "التكوير",
      "nameTransliteration": "At-Takwir",
      "nameTranslation": "The Overthrowing",
      "ayahCount": 29,
      "revelation": "Makkah",
      "ayahs": [
        {
          "number": 1,
          "textArabic": " إِذَا ٱلشَّمْسُ كُوِّرَتْ"
        },
        {
          "number": 2,
          "textArabic": "وَإِذَا ٱلنُّجُومُ ٱنكَدَرَتْ"
        },
        {
          "number": 3,
          "textArabic": "وَإِذَا ٱلْجِبَالُ سُيِّرَتْ"
        },
        {
          "number": 4,
          "textArabic": "وَإِذَا ٱلْعِشَارُ عُطِّلَتْ"
        },
        {
          "number": 5,
          "textArabic": "وَإِذَا ٱلْوُحُوشُ حُشِرَتْ"
        },
        {
          "number": 6,
          "textArabic": "وَإِذَا ٱلْبِحَارُ سُجِّرَتْ"
        },
        {
          "number": 7,
          "textArabic": "وَإِذَا ٱلنُّفُوسُ زُوِّجَتْ"
        },
        {
          "number": 8,
          "textArabic": "وَإِذَا ٱلْمَوْءُۥدَةُ سُئِلَتْ"
        },
        {
          "number": 9,
          "textArabic": "بِأَىِّ ذَنۢبٍ قُتِلَتْ"
        },
        {
          "number": 10,
          "textArabic": "وَإِذَا ٱلصُّحُفُ نُشِرَتْ"
        },
        {
          "number": 11,
          "textArabic": "وَإِذَا ٱلسَّمَآءُ كُشِطَتْ"
        },
        {
          "number": 12,
          "textArabic": "وَإِذَا ٱلْجَحِيمُ سُعِّرَتْ"
        },
        {
          "number": 13,
          "textArabic": "وَإِذَا ٱلْجَنَّةُ أُزْلِفَتْ"
        },
        {
          "number": 14,
          "textArabic": "عَلِمَتْ نَفْسٌ مَّآ أَحْضَرَتْ"
        },
        {
          "number": 15,
          "textArabic": "فَلَآ أُقْسِمُ بِٱلْخُنَّسِ"
        },
        {
          "number": 16,
          "textArabic": "ٱلْجَوَارِ ٱلْكُنَّسِ"
        },
        {
          "number": 17,
          "textArabic": "وَٱلَّيْلِ إِذَا عَسْعَسَ"
        },
        {
          "number": 18,
          "textArabic": "وَٱلصُّبْحِ إِذَا تَنَفَّسَ"
        },
        {
          "number": 19,
          "textArabic": "إِنَّهُۥ لَقَوْلُ رَسُولٍ كَرِيمٍ"
        },
        {
          "number": 20,
          "textArabic": "ذِى قُوَّةٍ عِندَ ذِى ٱلْعَرْشِ مَكِينٍ"
        },
        {
          "number": 21,
          "textArabic": "مُّطَاعٍ ثَمَّ أَمِينٍ"
        },
        {
          "number": 22,
          "textArabic": "وَمَا صَاحِبُكُم بِمَجْنُونٍ"
        },
        {
          "number": 23,
          "textArabic": "وَلَقَدْ رَءَاهُ بِٱلْأُفُقِ ٱلْمُبِينِ"
        },
        {
          "number": 24,
          "textArabic": "وَمَا هُوَ عَلَى ٱلْغَيْبِ بِضَنِينٍ"
        },
        {
          "number": 25,
          "textArabic": "وَمَا هُوَ بِقَوْلِ شَيْطَـٰنٍ رَّجِيمٍ"
        },
        {
          "number": 26,
          "textArabic": "فَأَيْنَ تَذْهَبُونَ"
        },
        {
          "number": 27,
          "textArabic": "إِنْ هُوَ إِلَّا ذِكْرٌ لِّلْعَـٰلَمِينَ"
        },
        {
          "number": 28,
          "textArabic": "لِمَن شَآءَ مِنكُمْ أَن يَسْتَقِيمَ"
        },
        {
          "number": 29,
          "textArabic": "وَمَا تَشَآءُونَ إِلَّآ أَن يَشَآءَ ٱللَّهُ رَبُّ ٱلْعَـٰلَمِينَ"
        }
      ]
    },
    {
      "number": 82,
      "nameArabic": "الانفطار",
      "nameTransliteration": "Al-Infitar",
      "nameTranslation": "The Cleaving",
      "ayahCount": 19,
      "revelation": "Makkah",
      "ayahs": [
        {
          "number": 1,
          "textArabic": " إِذَا ٱلسَّمَآءُ ٱنفَطَرَتْ"
        },
        {
          "number": 2,
          "textArabic": "وَإِذَا ٱلْكَوَاكِبُ ٱنتَثَرَتْ"
        },
        {
          "number": 3,
          "textArabic": "وَإِذَا ٱلْبِحَارُ فُجِّرَتْ"
        },
        {
          "number": 4,
          "textArabic": "وَإِذَا ٱلْقُبُورُ بُعْثِرَتْ"
        },
        {
          "number": 5,
          "textArabic": "عَلِمَتْ نَفْسٌ مَّا قَدَّمَتْ وَأَخَّرَتْ"
        },
        {
          "number": 6,
          "textArabic": "يَـٰٓأَيُّهَا ٱلْإِنسَـٰنُ مَا غَرَّكَ بِرَبِّكَ ٱلْكَرِيمِ"
        },
        {
          "number": 7,
          "textArabic": "ٱلَّذِى خَلَقَكَ فَسَوَّىٰكَ فَعَدَلَكَ"
        },
        {
          "number": 8,
          "textArabic": "فِىٓ أَىِّ صُورَةٍ مَّا شَآءَ رَكَّبَكَ"
        },
        {
          "number": 9,
          "textArabic": "كَلَّا بَلْ تُكَذِّبُونَ بِٱلدِّينِ"
        },
        {
          "number": 10,
          "textArabic": "وَإِنَّ عَلَيْكُمْ لَحَـٰفِظِينَ"
        },
        {
          "number": 11,
          "textArabic": "كِرَامًا كَـٰتِبِينَ"
        },
        {
          "number": 12,
          "textArabic": "يَعْلَمُونَ مَا تَفْعَلُونَ"
        },
        {
          "number": 13,
          "textArabic": "إِنَّ ٱلْأَبْرَارَ لَفِى نَعِيمٍ"
        },
        {
          "number": 14,
          "textArabic": "وَإِنَّ ٱلْفُجَّارَ لَفِى جَحِيمٍ"
        },
        {
          "number": 15,
          "textArabic": "يَصْلَوْنَهَا يَوْمَ ٱلدِّينِ"
        },
        {
          "number": 16,
          "textArabic": "وَمَا هُمْ عَنْهَا بِغَآئِبِينَ"
        },
        {
          "number": 17,
          "textArabic": "وَمَآ أَدْرَىٰكَ مَا يَوْمُ ٱلدِّينِ"
        },
        {
          "number": 18,
          "textArabic": "ثُمَّ مَآ أَدْرَىٰكَ مَا يَوْمُ ٱلدِّينِ"
        },
        {
          "number": 19,
          "textArabic": "يَوْمَ لَا تَمْلِكُ نَفْسٌ لِّنَفْسٍ شَيْـًٔا ۖ وَٱلْأَمْرُ يَوْمَئِذٍ لِّلَّهِ"
        }
      ]
    },
    {
      "number": 83,
      "nameArabic": "المطففين",
      "nameTransliteration": "Al-Mutaffifin",
      "nameTranslation": "The Defrauding",
      "ayahCount": 36,
      "revelation": "Makkah",
      "ayahs": [
        {
          "number": 1,
          "textArabic": " وَيْلٌ لِّلْمُطَفِّفِينَ"
        },
        {
          "number": 2,
          "textArabic": "ٱلَّذِينَ إِذَا ٱكْتَالُوا۟ عَلَى ٱلنَّاسِ يَسْتَوْفُونَ"
        },
        {
          "number": 3,
          "textArabic": "وَإِذَا كَالُوهُمْ أَو وَّزَنُوهُمْ يُخْسِرُونَ"
        },
        {
          "number": 4,
          "textArabic": "أَلَا يَظُنُّ أُو۟لَـٰٓئِكَ أَنَّهُم مَّبْعُوثُونَ"
        },
        {
          "number": 5,
          "textArabic": "لِيَوْمٍ عَظِيمٍ"
        },
        {
          "number": 6,
          "textArabic": "يَوْمَ يَقُومُ ٱلنَّاسُ لِرَبِّ ٱلْعَـٰلَمِينَ"
        },
        {
          "number": 7,
          "textArabic": "كَلَّآ إِنَّ كِتَـٰبَ ٱلْفُجَّارِ لَفِى سِجِّينٍ"
        },
        {
          "number": 8,
          "textArabic": "وَمَآ أَدْرَىٰكَ مَا سِجِّينٌ"
        },
        {
          "number": 9,
          "textArabic": "كِتَـٰبٌ مَّرْقُومٌ"
        },
        {
          "number": 10,
          "textArabic": "وَيْلٌ يَوْمَئِذٍ لِّلْمُكَذِّبِينَ"
        },
        {
          "number": 11,
          "textArabic": "ٱلَّذِينَ يُكَذِّبُونَ بِيَوْمِ ٱلدِّينِ"
        },
        {
          "number": 12,
          "textArabic": "وَمَا يُكَذِّبُ بِهِۦٓ إِلَّا كُلُّ مُعْتَدٍ أَثِيمٍ"
        },
        {
          "number": 13,
          "textArabic": "إِذَا تُتْلَىٰ عَلَيْهِ ءَايَـٰتُنَا قَالَ أَسَـٰطِيرُ ٱلْأَوَّلِينَ"
        },
        {
          "number": 14,
          "textArabic": "كَلَّا ۖ بَلْ ۜ رَانَ عَلَىٰ قُلُوبِهِم مَّا كَانُوا۟ يَكْسِبُونَ"
        },
        {
          "number": 15,
          "textArabic": "كَلَّآ إِنَّهُمْ عَن رَّبِّهِمْ يَوْمَئِذٍ لَّمَحْجُوبُونَ"
        },
        {
          "number": 16,
          "textArabic": "ثُمَّ إِنَّهُمْ لَصَالُوا۟ ٱلْجَحِيمِ"
        },
        {
          "number": 17,
          "textArabic": "ثُمَّ يُقَالُ هَـٰذَا ٱلَّذِى كُنتُم بِهِۦ تُكَذِّبُونَ"
        },
        {
          "number": 18,
          "textArabic": "كَلَّآ إِنَّ كِتَـٰبَ ٱلْأَبْرَارِ لَفِى عِلِّيِّينَ"
        },
        {
          "number": 19,
          "textArabic": "وَمَآ أَدْرَىٰكَ مَا عِلِّيُّونَ"
        },
        {
          "number": 20,
          "textArabic": "كِتَـٰبٌ مَّرْقُومٌ"
        },
        {
          "number": 21,
          "textArabic": "يَشْهَدُهُ ٱلْمُقَرَّبُونَ"
        },
        {
          "number": 22,
          "textArabic": "إِنَّ ٱلْأَبْرَارَ لَفِى نَعِيمٍ"
        },
        {
          "number": 23,
          "textArabic": "عَلَى ٱلْأَرَآئِكِ يَنظُرُونَ"
        },
        {
          "number": 24,
          "textArabic": "تَعْرِفُ فِى وُجُوهِهِمْ نَضْرَةَ ٱلنَّعِيمِ"
        },
        {
          "number": 25,
          "textArabic": "يُسْقَوْنَ مِن رَّحِيقٍ مَّخْتُومٍ"
        },
        {
          "number": 26,
          "textArabic": "خِتَـٰمُهُۥ مِسْكٌ ۚ وَفِى ذَٰلِكَ فَلْيَتَنَافَسِ ٱلْمُتَنَـٰفِسُونَ"
        },
        {
          "number": 27,
          "textArabic": "وَمِزَاجُهُۥ مِن تَسْنِيمٍ"
        },
        {
          "number": 28,
          "textArabic": "عَيْنًا يَشْرَبُ بِهَا ٱلْمُقَرَّبُونَ"
        },
        {
          "number": 29,
          "textArabic": "إِنَّ ٱلَّذِينَ أَجْرَمُوا۟ كَانُوا۟ مِنَ ٱلَّذِينَ ءَامَنُوا۟ يَضْحَكُونَ"
        },
        {
          "number": 30,
          "textArabic": "وَإِذَا مَرُّوا۟ بِهِمْ يَتَغَامَزُونَ"
        },
        {
          "number": 31,
          "textArabic": "وَإِذَا ٱنقَلَبُوٓا۟ إِلَىٰٓ أَهْلِهِمُ ٱنقَلَبُوا۟ فَكِهِينَ"
        },
        {
          "number": 32,
          "textArabic": "وَإِذَا رَأَوْهُمْ قَالُوٓا۟ إِنَّ هَـٰٓؤُلَآءِ لَضَآلُّونَ"
        },
        {
          "number": 33,
          "textArabic": "وَمَآ أُرْسِلُوا۟ عَلَيْهِمْ حَـٰفِظِينَ"
        },
        {
          "number": 34,
          "textArabic": "فَٱلْيَوْمَ ٱلَّذِينَ ءَامَنُوا۟ مِنَ ٱلْكُفَّارِ يَضْحَكُونَ"
        },
        {
          "number": 35,
          "textArabic": "عَلَى ٱلْأَرَآئِكِ يَنظُرُونَ"
        },
        {
          "number": 36,
          "textArabic": "هَلْ ثُوِّبَ ٱلْكُفَّارُ مَا كَانُوا۟ يَفْعَلُونَ"
        }
      ]
    },
    {
      "number": 84,
      "nameArabic": "الانشقاق",
      "nameTransliteration": "Al-Inshiqaq",
      "nameTranslation": "The Splitting Asunder",
      "ayahCount": 25,
      "revelation": "Makkah",
      "ayahs": [
        {
          "number": 1,
          "textArabic": " إِذَا ٱلسَّمَآءُ ٱنشَقَّتْ"
        },
        {
          "number": 2,
          "textArabic": "وَأَذِنَتْ لِرَبِّهَا وَحُقَّتْ"
        },
        {
          "number": 3,
          "textArabic": "وَإِذَا ٱلْأَرْضُ مُدَّتْ"
        },
        {
          "number": 4,
          "textArabic": "وَأَلْقَتْ مَا فِيهَا وَتَخَلَّتْ"
        },
        {
          "number": 5,
          "textArabic": "وَأَذِنَتْ لِرَبِّهَا وَحُقَّتْ"
        },
        {
          "number": 6,
          "textArabic": "يَـٰٓأَيُّهَا ٱلْإِنسَـٰنُ إِنَّكَ كَادِحٌ إِلَىٰ رَبِّكَ كَدْحًا فَمُلَـٰقِيهِ"
        },
        {
          "number": 7,
          "textArabic": "فَأَمَّا مَنْ أُوتِىَ كِتَـٰبَهُۥ بِيَمِينِهِۦ"
        },
        {
          "number": 8,
          "textArabic": "فَسَوْفَ يُحَاسَبُ حِسَابًا يَسِيرًا"
        },
        {
          "number": 9,
          "textArabic": "وَيَنقَلِبُ إِلَىٰٓ أَهْلِهِۦ مَسْرُورًا"
        },
        {
          "number": 10,
          "textArabic": "وَأَمَّا مَنْ أُوتِىَ كِتَـٰبَهُۥ وَرَآءَ ظَهْرِهِۦ"
        },
        {
          "number": 11,
          "textArabic": "فَسَوْفَ يَدْعُوا۟ ثُبُورًا"
        },
        {
          "number": 12,
          "textArabic": "وَيَصْلَىٰ سَعِيرًا"
        },
        {
          "number": 13,
          "textArabic": "إِنَّهُۥ كَانَ فِىٓ أَهْلِهِۦ مَسْرُورًا"
        },
        {
          "number": 14,
          "textArabic": "إِنَّهُۥ ظَنَّ أَن لَّن يَحُورَ"
        },
        {
          "number": 15,
          "textArabic": "بَلَىٰٓ إِنَّ رَبَّهُۥ كَانَ بِهِۦ بَصِيرًا"
        },
        {
          "number": 16,
          "textArabic": "فَلَآ أُقْسِمُ بِٱلشَّفَقِ"
        },
        {
          "number": 17,
          "textArabic": "وَٱلَّيْلِ وَمَا وَسَقَ"
        },
        {
          "number": 18,
          "textArabic": "وَٱلْقَمَرِ إِذَا ٱتَّسَقَ"
        },
        {
          "number": 19,
          "textArabic": "لَتَرْكَبُنَّ طَبَقًا عَن طَبَقٍ"
        },
        {
          "number": 20,
          "textArabic": "فَمَا لَهُمْ لَا يُؤْمِنُونَ"
        },
        {
          "number": 21,
          "textArabic": "وَإِذَا قُرِئَ عَلَيْهِمُ ٱلْقُرْءَانُ لَا يَسْجُدُونَ ۩"
        },
        {
          "number": 22,
          "textArabic": "بَلِ ٱلَّذِينَ كَفَرُوا۟ يُكَذِّبُونَ"
        },
        {
          "number": 23,
          "textArabic": "وَٱللَّهُ أَعْلَمُ بِمَا يُوعُونَ"
        },
        {
          "number": 24,
          "textArabic": "فَبَشِّرْهُم بِعَذَابٍ أَلِيمٍ"
        },
        {
          "number": 25,
          "textArabic": "إِلَّا ٱلَّذِينَ ءَامَنُوا۟ وَعَمِلُوا۟ ٱلصَّـٰلِحَـٰتِ لَهُمْ أَجْرٌ غَيْرُ مَمْنُونٍۭ"
        }
      ]
    },
    {
      "number": 85,
      "nameArabic": "البروج",
      "nameTransliteration": "Al-Buruj",
      "nameTranslation": "The Stars",
      "ayahCount": 22,
      "revelation": "Makkah",
      "ayahs": [
        {
          "number": 1,
          "textArabic": " وَٱلسَّمَآءِ ذَاتِ ٱلْبُرُوجِ"
        },
        {
          "number": 2,
          "textArabic": "وَٱلْيَوْمِ ٱلْمَوْعُودِ"
        },
        {
          "number": 3,
          "textArabic": "وَشَاهِدٍ وَمَشْهُودٍ"
        },
        {
          "number": 4,
          "textArabic": "قُتِلَ أَصْحَـٰبُ ٱلْأُخْدُودِ"
        },
        {
          "number": 5,
          "textArabic": "ٱلنَّارِ ذَاتِ ٱلْوَقُودِ"
        },
        {
          "number": 6,
          "textArabic": "إِذْ هُمْ عَلَيْهَا قُعُودٌ"
        },
        {
          "number": 7,
          "textArabic": "وَهُمْ عَلَىٰ مَا يَفْعَلُونَ بِٱلْمُؤْمِنِينَ شُهُودٌ"
        },
        {
          "number": 8,
          "textArabic": "وَمَا نَقَمُوا۟ مِنْهُمْ إِلَّآ أَن يُؤْمِنُوا۟ بِٱللَّهِ ٱلْعَزِيزِ ٱلْحَمِيدِ"
        },
        {
          "number": 9,
          "textArabic": "ٱلَّذِى لَهُۥ مُلْكُ ٱلسَّمَـٰوَٰتِ وَٱلْأَرْضِ ۚ وَٱللَّهُ عَلَىٰ كُلِّ شَىْءٍ شَهِيدٌ"
        },
        {
          "number": 10,
          "textArabic": "إِنَّ ٱلَّذِينَ فَتَنُوا۟ ٱلْمُؤْمِنِينَ وَٱلْمُؤْمِنَـٰتِ ثُمَّ لَمْ يَتُوبُوا۟ فَلَهُمْ عَذَابُ جَهَنَّمَ وَلَهُمْ عَذَابُ ٱلْحَرِيقِ"
        },
        {
          "number": 11,
          "textArabic": "إِنَّ ٱلَّذِينَ ءَامَنُوا۟ وَعَمِلُوا۟ ٱلصَّـٰلِحَـٰتِ لَهُمْ جَنَّـٰتٌ تَجْرِى مِن تَحْتِهَا ٱلْأَنْهَـٰرُ ۚ ذَٰلِكَ ٱلْفَوْزُ ٱلْكَبِيرُ"
        },
        {
          "number": 12,
          "textArabic": "إِنَّ بَطْشَ رَبِّكَ لَشَدِيدٌ"
        },
        {
          "number": 13,
          "textArabic": "إِنَّهُۥ هُوَ يُبْدِئُ وَيُعِيدُ"
        },
        {
          "number": 14,
          "textArabic": "وَهُوَ ٱلْغَفُورُ ٱلْوَدُودُ"
        },
        {
          "number": 15,
          "textArabic": "ذُو ٱلْعَرْشِ ٱلْمَجِيدُ"
        },
        {
          "number": 16,
          "textArabic": "فَعَّالٌ لِّمَا يُرِيدُ"
        },
        {
          "number": 17,
          "textArabic": "هَلْ أَتَىٰكَ حَدِيثُ ٱلْجُنُودِ"
        },
        {
          "number": 18,
          "textArabic": "فِرْعَوْنَ وَثَمُودَ"
        },
        {
          "number": 19,
          "textArabic": "بَلِ ٱلَّذِينَ كَفَرُوا۟ فِى تَكْذِيبٍ"
        },
        {
          "number": 20,
          "textArabic": "وَٱللَّهُ مِن وَرَآئِهِم مُّحِيطٌۢ"
        },
        {
          "number": 21,
          "textArabic": "بَلْ هُوَ قُرْءَانٌ مَّجِيدٌ"
        },
        {
          "number": 22,
          "textArabic": "فِى لَوْحٍ مَّحْفُوظٍۭ"
        }
      ]
    },
    {
      "number": 86,
      "nameArabic": "الطارق",
      "nameTransliteration": "At-Tariq",
      "nameTranslation": "The Nightcomer",
      "ayahCount": 17,
      "revelation": "Makkah",
      "ayahs": [
        {
          "number": 1,
          "textArabic": " وَٱلسَّمَآءِ وَٱلطَّارِقِ"
        },
        {
          "number": 2,
          "textArabic": "وَمَآ أَدْرَىٰكَ مَا ٱلطَّارِقُ"
        },
        {
          "number": 3,
          "textArabic": "ٱلنَّجْمُ ٱلثَّاقِبُ"
        },
        {
          "number": 4,
          "textArabic": "إِن كُلُّ نَفْسٍ لَّمَّا عَلَيْهَا حَافِظٌ"
        },
        {
          "number": 5,
          "textArabic": "فَلْيَنظُرِ ٱلْإِنسَـٰنُ مِمَّ خُلِقَ"
        },
        {
          "number": 6,
          "textArabic": "خُلِقَ مِن مَّآءٍ دَافِقٍ"
        },
        {
          "number": 7,
          "textArabic": "يَخْرُجُ مِنۢ بَيْنِ ٱلصُّلْبِ وَٱلتَّرَآئِبِ"
        },
        {
          "number": 8,
          "textArabic": "إِنَّهُۥ عَلَىٰ رَجْعِهِۦ لَقَادِرٌ"
        },
        {
          "number": 9,
          "textArabic": "يَوْمَ تُبْلَى ٱلسَّرَآئِرُ"
        },
        {
          "number": 10,
          "textArabic": "فَمَا لَهُۥ مِن قُوَّةٍ وَلَا نَاصِرٍ"
        },
        {
          "number": 11,
          "textArabic": "وَٱلسَّمَآءِ ذَاتِ ٱلرَّجْعِ"
        },
        {
          "number": 12,
          "textArabic": "وَٱلْأَرْضِ ذَاتِ ٱلصَّدْعِ"
        },
        {
          "number": 13,
          "textArabic": "إِنَّهُۥ لَقَوْلٌ فَصْلٌ"
        },
        {
          "number": 14,
          "textArabic": "وَمَا هُوَ بِٱلْهَزْلِ"
        },
        {
          "number": 15,
          "textArabic": "إِنَّهُمْ يَكِيدُونَ كَيْدًا"
        },
        {
          "number": 16,
          "textArabic": "وَأَكِيدُ كَيْدًا"
        },
        {
          "number": 17,
          "textArabic": "فَمَهِّلِ ٱلْكَـٰفِرِينَ أَمْهِلْهُمْ رُوَيْدًۢا"
        }
      ]
    },
    {
      "number": 87,
      "nameArabic": "الأعلى",
      "nameTransliteration": "Al-A'la",
      "nameTranslation": "The Most High",
      "ayahCount": 19,
      "revelation": "Makkah",
      "ayahs": [
        {
          "number": 1,
          "textArabic": " سَبِّحِ ٱسْمَ رَبِّكَ ٱلْأَعْلَى"
        },
        {
          "number": 2,
          "textArabic": "ٱلَّذِى خَلَقَ فَسَوَّىٰ"
        },
        {
          "number": 3,
          "textArabic": "وَٱلَّذِى قَدَّرَ فَهَدَىٰ"
        },
        {
          "number": 4,
          "textArabic": "وَٱلَّذِىٓ أَخْرَجَ ٱلْمَرْعَىٰ"
        },
        {
          "number": 5,
          "textArabic": "فَجَعَلَهُۥ غُثَآءً أَحْوَىٰ"
        },
        {
          "number": 6,
          "textArabic": "سَنُقْرِئُكَ فَلَا تَنسَىٰٓ"
        },
        {
          "number": 7,
          "textArabic": "إِلَّا مَا شَآءَ ٱللَّهُ ۚ إِنَّهُۥ يَعْلَمُ ٱلْجَهْرَ وَمَا يَخْفَىٰ"
        },
        {
          "number": 8,
          "textArabic": "وَنُيَسِّرُكَ لِلْيُسْرَىٰ"
        },
        {
          "number": 9,
          "textArabic": "فَذَكِّرْ إِن نَّفَعَتِ ٱلذِّكْرَىٰ"
        },
        {
          "number": 10,
          "textArabic": "سَيَذَّكَّرُ مَن يَخْشَىٰ"
        },
        {
          "number": 11,
          "textArabic": "وَيَتَجَنَّبُهَا ٱلْأَشْقَى"
        },
        {
          "number": 12,
          "textArabic": "ٱلَّذِى يَصْلَى ٱلنَّارَ ٱلْكُبْرَىٰ"
        },
        {
          "number": 13,
          "textArabic": "ثُمَّ لَا يَمُوتُ فِيهَا وَلَا يَحْيَىٰ"
        },
        {
          "number": 14,
          "textArabic": "قَدْ أَفْلَحَ مَن تَزَكَّىٰ"
        },
        {
          "number": 15,
          "textArabic": "وَذَكَرَ ٱسْمَ رَبِّهِۦ فَصَلَّىٰ"
        },
        {
          "number": 16,
          "textArabic": "بَلْ تُؤْثِرُونَ ٱلْحَيَوٰةَ ٱلدُّنْيَا"
        },
        {
          "number": 17,
          "textArabic": "وَٱلْـَٔاخِرَةُ خَيْرٌ وَأَبْقَىٰٓ"
        },
        {
          "number": 18,
          "textArabic": "إِنَّ هَـٰذَا لَفِى ٱلصُّحُفِ ٱلْأُولَىٰ"
        },
        {
          "number": 19,
          "textArabic": "صُحُفِ إِبْرَٰهِيمَ وَمُوسَىٰ"
        }
      ]
    },
    {
      "number": 88,
      "nameArabic": "الغاشية",
      "nameTransliteration": "Al-Ghashiyah",
      "nameTranslation": "The Overwhelming",
      "ayahCount": 26,
      "revelation": "Makkah",
      "ayahs": [
        {
          "number": 1,
          "textArabic": " هَلْ أَتَىٰكَ حَدِيثُ ٱلْغَـٰشِيَةِ"
        },
        {
          "number": 2,
          "textArabic": "وُجُوهٌ يَوْمَئِذٍ خَـٰشِعَةٌ"
        },
        {
          "number": 3,
          "textArabic": "عَامِلَةٌ نَّاصِبَةٌ"
        },
        {
          "number": 4,
          "textArabic": "تَصْلَىٰ نَارًا حَامِيَةً"
        },
        {
          "number": 5,
          "textArabic": "تُسْقَىٰ مِنْ عَيْنٍ ءَانِيَةٍ"
        },
        {
          "number": 6,
          "textArabic": "لَّيْسَ لَهُمْ طَعَامٌ إِلَّا مِن ضَرِيعٍ"
        },
        {
          "number": 7,
          "textArabic": "لَّا يُسْمِنُ وَلَا يُغْنِى مِن جُوعٍ"
        },
        {
          "number": 8,
          "textArabic": "وُجُوهٌ يَوْمَئِذٍ نَّاعِمَةٌ"
        },
        {
          "number": 9,
          "textArabic": "لِّسَعْيِهَا رَاضِيَةٌ"
        },
        {
          "number": 10,
          "textArabic": "فِى جَنَّةٍ عَالِيَةٍ"
        },
        {
          "number": 11,
          "textArabic": "لَّا تَسْمَعُ فِيهَا لَـٰغِيَةً"
        },
        {
          "number": 12,
          "textArabic": "فِيهَا عَيْنٌ جَارِيَةٌ"
        },
        {
          "number": 13,
          "textArabic": "فِيهَا سُرُرٌ مَّرْفُوعَةٌ"
        },
        {
          "number": 14,
          "textArabic": "وَأَكْوَابٌ مَّوْضُوعَةٌ"
        },
        {
          "number": 15,
          "textArabic": "وَنَمَارِقُ مَصْفُوفَةٌ"
        },
        {
          "number": 16,
          "textArabic": "وَزَرَابِىُّ مَبْثُوثَةٌ"
        },
        {
          "number": 17,
          "textArabic": "أَفَلَا يَنظُرُونَ إِلَى ٱلْإِبِلِ كَيْفَ خُلِقَتْ"
        },
        {
          "number": 18,
          "textArabic": "وَإِلَى ٱلسَّمَآءِ كَيْفَ رُفِعَتْ"
        },
        {
          "number": 19,
          "textArabic": "وَإِلَى ٱلْجِبَالِ كَيْفَ نُصِبَتْ"
        },
        {
          "number": 20,
          "textArabic": "وَإِلَى ٱلْأَرْضِ كَيْفَ سُطِحَتْ"
        },
        {
          "number": 21,
          "textArabic": "فَذَكِّرْ إِنَّمَآ أَنتَ مُذَكِّرٌ"
        },
        {
          "number": 22,
          "textArabic": "لَّسْتَ عَلَيْهِم بِمُصَيْطِرٍ"
        },
        {
          "number": 23,
          "textArabic": "إِلَّا مَن تَوَلَّىٰ وَكَفَرَ"
        },
        {
          "number": 24,
          "textArabic": "فَيُعَذِّبُهُ ٱللَّهُ ٱلْعَذَابَ ٱلْأَكْبَرَ"
        },
        {
          "number": 25,
          "textArabic": "إِنَّ إِلَيْنَآ إِيَابَهُمْ"
        },
        {
          "number": 26,
          "textArabic": "ثُمَّ إِنَّ عَلَيْنَا حِسَابَهُم"
        }
      ]
    },
    {
      "number": 89,
      "nameArabic": "الفجر",
      "nameTransliteration": "Al-Fajr",
      "nameTranslation": "The Dawn",
      "ayahCount": 30,
      "revelation": "Makkah",
      "ayahs": [
        {
          "number": 1,
          "textArabic": " وَٱلْفَجْرِ"
        },
        {
          "number": 2,
          "textArabic": "وَلَيَالٍ عَشْرٍ"
        },
        {
          "number": 3,
          "textArabic": "وَٱلشَّفْعِ وَٱلْوَتْرِ"
        },
        {
          "number": 4,
          "textArabic": "وَٱلَّيْلِ إِذَا يَسْرِ"
        },
        {
          "number": 5,
          "textArabic": "هَلْ فِى ذَٰلِكَ قَسَمٌ لِّذِى حِجْرٍ"
        },
        {
          "number": 6,
          "textArabic": "أَلَمْ تَرَ كَيْفَ فَعَلَ رَبُّكَ بِعَادٍ"
        },
        {
          "number": 7,
          "textArabic": "إِرَمَ ذَاتِ ٱلْعِمَادِ"
        },
        {
          "number": 8,
          "textArabic": "ٱلَّتِى لَمْ يُخْلَقْ مِثْلُهَا فِى ٱلْبِلَـٰدِ"
        },
        {
          "number": 9,
          "textArabic": "وَثَمُودَ ٱلَّذِينَ جَابُوا۟ ٱلصَّخْرَ بِٱلْوَادِ"
        },
        {
          "number": 10,
          "textArabic": "وَفِرْعَوْنَ ذِى ٱلْأَوْتَادِ"
        },
        {
          "number": 11,
          "textArabic": "ٱلَّذِينَ طَغَوْا۟ فِى ٱلْبِلَـٰدِ"
        },
        {
          "number": 12,
          "textArabic": "فَأَكْثَرُوا۟ فِيهَا ٱلْفَسَادَ"
        },
        {
          "number": 13,
          "textArabic": "فَصَبَّ عَلَيْهِمْ رَبُّكَ سَوْطَ عَذَابٍ"
        },
        {
          "number": 14,
          "textArabic": "إِنَّ رَبَّكَ لَبِٱلْمِرْصَادِ"
        },
        {
          "number": 15,
          "textArabic": "فَأَمَّا ٱلْإِنسَـٰنُ إِذَا مَا ٱبْتَلَىٰهُ رَبُّهُۥ فَأَكْرَمَهُۥ وَنَعَّمَهُۥ فَيَقُولُ رَبِّىٓ أَكْرَمَنِ"
        },
        {
          "number": 16,
          "textArabic": "وَأَمَّآ إِذَا مَا ٱبْتَلَىٰهُ فَقَدَرَ عَلَيْهِ رِزْقَهُۥ فَيَقُولُ رَبِّىٓ أَهَـٰنَنِ"
        },
        {
          "number": 17,
          "textArabic": "كَلَّا ۖ بَل لَّا تُكْرِمُونَ ٱلْيَتِيمَ"
        },
        {
          "number": 18,
          "textArabic": "وَلَا تَحَـٰٓضُّونَ عَلَىٰ طَعَامِ ٱلْمِسْكِينِ"
        },
        {
          "number": 19,
          "textArabic": "وَتَأْكُلُونَ ٱلتُّرَاثَ أَكْلًا لَّمًّا"
        },
        {
          "number": 20,
          "textArabic": "وَتُحِبُّونَ ٱلْمَالَ حُبًّا جَمًّا"
        },
        {
          "number": 21,
          "textArabic": "كَلَّآ إِذَا دُكَّتِ ٱلْأَرْضُ دَكًّا دَكًّا"
        },
        {
          "number": 22,
          "textArabic": "وَجَآءَ رَبُّكَ وَٱلْمَلَكُ صَفًّا صَفًّا"
        },
        {
          "number": 23,
          "textArabic": "وَجِا۟ىٓءَ يَوْمَئِذٍۭ بِجَهَنَّمَ ۚ يَوْمَئِذٍ يَتَذَكَّرُ ٱلْإِنسَـٰنُ وَأَنَّىٰ لَهُ ٱلذِّكْرَىٰ"
        },
        {
          "number": 24,
          "textArabic": "يَقُولُ يَـٰلَيْتَنِى قَدَّمْتُ لِحَيَاتِى"
        },
        {
          "number": 25,
          "textArabic": "فَيَوْمَئِذٍ لَّا يُعَذِّبُ عَذَابَهُۥٓ أَحَدٌ"
        },
        {
          "number": 26,
          "textArabic": "وَلَا يُوثِقُ وَثَاقَهُۥٓ أَحَدٌ"
        },
        {
          "number": 27,
          "textArabic": "يَـٰٓأَيَّتُهَا ٱلنَّفْسُ ٱلْمُطْمَئِنَّةُ"
        },
        {
          "number": 28,
          "textArabic": "ٱرْجِعِىٓ إِلَىٰ رَبِّكِ رَاضِيَةً مَّرْضِيَّةً"
        },
        {
          "number": 29,
          "textArabic": "فَٱدْخُلِى فِى عِبَـٰدِى"
        },
        {
          "number": 30,
          "textArabic": "وَٱدْخُلِى جَنَّتِى"
        }
      ]
    },
    {
      "number": 90,
      "nameArabic": "البلد",
      "nameTransliteration": "Al-Balad",
      "nameTranslation": "The City",
      "ayahCount": 20,
      "revelation": "Makkah",
      "ayahs": [
        {
          "number": 1,
          "textArabic": " لَآ أُقْسِمُ بِهَـٰذَا ٱلْبَلَدِ"
        },
        {
          "number": 2,
          "textArabic": "وَأَنتَ حِلٌّۢ بِهَـٰذَا ٱلْبَلَدِ"
        },
        {
          "number": 3,
          "textArabic": "وَوَالِدٍ وَمَا وَلَدَ"
        },
        {
          "number": 4,
          "textArabic": "لَقَدْ خَلَقْنَا ٱلْإِنسَـٰنَ فِى كَبَدٍ"
        },
        {
          "number": 5,
          "textArabic": "أَيَحْسَبُ أَن لَّن يَقْدِرَ عَلَيْهِ أَحَدٌ"
        },
        {
          "number": 6,
          "textArabic": "يَقُولُ أَهْلَكْتُ مَالًا لُّبَدًا"
        },
        {
          "number": 7,
          "textArabic": "أَيَحْسَبُ أَن لَّمْ يَرَهُۥٓ أَحَدٌ"
        },
        {
          "number": 8,
          "textArabic": "أَلَمْ نَجْعَل لَّهُۥ عَيْنَيْنِ"
        },
        {
          "number": 9,
          "textArabic": "وَلِسَانًا وَشَفَتَيْنِ"
        },
        {
          "number": 10,
          "textArabic": "وَهَدَيْنَـٰهُ ٱلنَّجْدَيْنِ"
        },
        {
          "number": 11,
          "textArabic": "فَلَا ٱقْتَحَمَ ٱلْعَقَبَةَ"
        },
        {
          "number": 12,
          "textArabic": "وَمَآ أَدْرَىٰكَ مَا ٱلْعَقَبَةُ"
        },
        {
          "number": 13,
          "textArabic": "فَكُّ رَقَبَةٍ"
        },
        {
          "number": 14,
          "textArabic": "أَوْ إِطْعَـٰمٌ فِى يَوْمٍ ذِى مَسْغَبَةٍ"
        },
        {
          "number": 15,
          "textArabic": "يَتِيمًا ذَا مَقْرَبَةٍ"
        },
        {
          "number": 16,
          "textArabic": "أَوْ مِسْكِينًا ذَا مَتْرَبَةٍ"
        },
        {
          "number": 17,
          "textArabic": "ثُمَّ كَانَ مِنَ ٱلَّذِينَ ءَامَنُوا۟ وَتَوَاصَوْا۟ بِٱلصَّبْرِ وَتَوَاصَوْا۟ بِٱلْمَرْحَمَةِ"
        },
        {
          "number": 18,
          "textArabic": "أُو۟لَـٰٓئِكَ أَصْحَـٰبُ ٱلْمَيْمَنَةِ"
        },
        {
          "number": 19,
          "textArabic": "وَٱلَّذِينَ كَفَرُوا۟ بِـَٔايَـٰتِنَا هُمْ أَصْحَـٰبُ ٱلْمَشْـَٔمَةِ"
        },
        {
          "number": 20,
          "textArabic": "عَلَيْهِمْ نَارٌ مُّؤْصَدَةٌۢ"
        }
      ]
    },
    {
      "number": 91,
      "nameArabic": "الشمس",
      "nameTransliteration": "Ash-Shams",
      "nameTranslation": "The Sun",
      "ayahCount": 15,
      "revelation": "Makkah",
      "ayahs": [
        {
          "number": 1,
          "textArabic": " وَٱلشَّمْسِ وَضُحَىٰهَا"
        },
        {
          "number": 2,
          "textArabic": "وَٱلْقَمَرِ إِذَا تَلَىٰهَا"
        },
        {
          "number": 3,
          "textArabic": "وَٱلنَّهَارِ إِذَا جَلَّىٰهَا"
        },
        {
          "number": 4,
          "textArabic": "وَٱلَّيْلِ إِذَا يَغْشَىٰهَا"
        },
        {
          "number": 5,
          "textArabic": "وَٱلسَّمَآءِ وَمَا بَنَىٰهَا"
        },
        {
          "number": 6,
          "textArabic": "وَٱلْأَرْضِ وَمَا طَحَىٰهَا"
        },
        {
          "number": 7,
          "textArabic": "وَنَفْسٍ وَمَا سَوَّىٰهَا"
        },
        {
          "number": 8,
          "textArabic": "فَأَلْهَمَهَا فُجُورَهَا وَتَقْوَىٰهَا"
        },
        {
          "number": 9,
          "textArabic": "قَدْ أَفْلَحَ مَن زَكَّىٰهَا"
        },
        {
          "number": 10,
          "textArabic": "وَقَدْ خَابَ مَن دَسَّىٰهَا"
        },
        {
          "number": 11,
          "textArabic": "كَذَّبَتْ ثَمُودُ بِطَغْوَىٰهَآ"
        },
        {
          "number": 12,
          "textArabic": "إِذِ ٱنۢبَعَثَ أَشْقَىٰهَا"
        },
        {
          "number": 13,
          "textArabic": "فَقَالَ لَهُمْ رَسُولُ ٱللَّهِ نَاقَةَ ٱللَّهِ وَسُقْيَـٰهَا"
        },
        {
          "number": 14,
          "textArabic": "فَكَذَّبُوهُ فَعَقَرُوهَا فَدَمْدَمَ عَلَيْهِمْ رَبُّهُم بِذَنۢبِهِمْ فَسَوَّىٰهَا"
        },
        {
          "number": 15,
          "textArabic": "وَلَا يَخَافُ عُقْبَـٰهَا"
        }
      ]
    },
    {
      "number": 92,
      "nameArabic": "الليل",
      "nameTransliteration": "Al-Layl",
      "nameTranslation": "The Night",
      "ayahCount": 21,
      "revelation": "Makkah",
      "ayahs": [
        {
          "number": 1,
          "textArabic": " وَٱلَّيْلِ إِذَا يَغْشَىٰ"
        },
        {
          "number": 2,
          "textArabic": "وَٱلنَّهَارِ إِذَا تَجَلَّىٰ"
        },
        {
          "number": 3,
          "textArabic": "وَمَا خَلَقَ ٱلذَّكَرَ وَٱلْأُنثَىٰٓ"
        },
        {
          "number": 4,
          "textArabic": "إِنَّ سَعْيَكُمْ لَشَتَّىٰ"
        },
        {
          "number": 5,
          "textArabic": "فَأَمَّا مَنْ أَعْطَىٰ وَٱتَّقَىٰ"
        },
        {
          "number": 6,
          "textArabic": "وَصَدَّقَ بِٱلْحُسْنَىٰ"
        },
        {
          "number": 7,
          "textArabic": "فَسَنُيَسِّرُهُۥ لِلْيُسْرَىٰ"
        },
        {
          "number": 8,
          "textArabic": "وَأَمَّا مَنۢ بَخِلَ وَٱسْتَغْنَىٰ"
        },
        {
          "number": 9,
          "textArabic": "وَكَذَّبَ بِٱلْحُسْنَىٰ"
        },
        {
          "number": 10,
          "textArabic": "فَسَنُيَسِّرُهُۥ لِلْعُسْرَىٰ"
        },
        {
          "number": 11,
          "textArabic": "وَمَا يُغْنِى عَنْهُ مَالُهُۥٓ إِذَا تَرَدَّىٰٓ"
        },
        {
          "number": 12,
          "textArabic": "إِنَّ عَلَيْنَا لَلْهُدَىٰ"
        },
        {
          "number": 13,
          "textArabic": "وَإِنَّ لَنَا لَلْـَٔاخِرَةَ وَٱلْأُولَىٰ"
        },
        {
          "number": 14,
          "textArabic": "فَأَنذَرْتُكُمْ نَارًا تَلَظَّىٰ"
        },
        {
          "number": 15,
          "textArabic": "لَا يَصْلَىٰهَآ إِلَّا ٱلْأَشْقَى"
        },
        {
          "number": 16,
          "textArabic": "ٱلَّذِى كَذَّبَ وَتَوَلَّىٰ"
        },
        {
          "number": 17,
          "textArabic": "وَسَيُجَنَّبُهَا ٱلْأَتْقَى"
        },
        {
          "number": 18,
          "textArabic": "ٱلَّذِى يُؤْتِى مَالَهُۥ يَتَزَكَّىٰ"
        },
        {
          "number": 19,
          "textArabic": "وَمَا لِأَحَدٍ عِندَهُۥ مِن نِّعْمَةٍ تُجْزَىٰٓ"
        },
        {
          "number": 20,
          "textArabic": "إِلَّا ٱبْتِغَآءَ وَجْهِ رَبِّهِ ٱلْأَعْلَىٰ"
        },
        {
          "number": 21,
          "textArabic": "وَلَسَوْفَ يَرْضَىٰ"
        }
      ]
    },
    {
      "number": 93,
      "nameArabic": "الضحى",
      "nameTransliteration": "Ad-Duha",
      "nameTranslation": "The Forenoon",
      "ayahCount": 11,
      "revelation": "Makkah",
      "ayahs": [
        {
          "number": 1,
          "textArabic": " وَٱلضُّحَىٰ"
        },
        {
          "number": 2,
          "textArabic": "وَٱلَّيْلِ إِذَا سَجَىٰ"
        },
        {
          "number": 3,
          "textArabic": "مَا وَدَّعَكَ رَبُّكَ وَمَا قَلَىٰ"
        },
        {
          "number": 4,
          "textArabic": "وَلَلْـَٔاخِرَةُ خَيْرٌ لَّكَ مِنَ ٱلْأُولَىٰ"
        },
        {
          "number": 5,
          "textArabic": "وَلَسَوْفَ يُعْطِيكَ رَبُّكَ فَتَرْضَىٰٓ"
        },
        {
          "number": 6,
          "textArabic": "أَلَمْ يَجِدْكَ يَتِيمًا فَـَٔاوَىٰ"
        },
        {
          "number": 7,
          "textArabic": "وَوَجَدَكَ ضَآلًّا فَهَدَىٰ"
        },
        {
          "number": 8,
          "textArabic": "وَوَجَدَكَ عَآئِلًا فَأَغْنَىٰ"
        },
        {
          "number": 9,
          "textArabic": "فَأَمَّا ٱلْيَتِيمَ فَلَا تَقْهَرْ"
        },
        {
          "number": 10,
          "textArabic": "وَأَمَّا ٱلسَّآئِلَ فَلَا تَنْهَرْ"
        },
        {
          "number": 11,
          "textArabic": "وَأَمَّا بِنِعْمَةِ رَبِّكَ فَحَدِّثْ"
        }
      ]
    },
    {
      "number": 94,
      "nameArabic": "الشرح",
      "nameTransliteration": "Ash-Sharh",
      "nameTranslation": "The Opening Forth",
      "ayahCount": 8,
      "revelation": "Makkah",
      "ayahs": [
        {
          "number": 1,
          "textArabic": " أَلَمْ نَشْرَحْ لَكَ صَدْرَكَ"
        },
        {
          "number": 2,
          "textArabic": "وَوَضَعْنَا عَنكَ وِزْرَكَ"
        },
        {
          "number": 3,
          "textArabic": "ٱلَّذِىٓ أَنقَضَ ظَهْرَكَ"
        },
        {
          "number": 4,
          "textArabic": "وَرَفَعْنَا لَكَ ذِكْرَكَ"
        },
        {
          "number": 5,
          "textArabic": "فَإِنَّ مَعَ ٱلْعُسْرِ يُسْرًا"
        },
        {
          "number": 6,
          "textArabic": "إِنَّ مَعَ ٱلْعُسْرِ يُسْرًا"
        },
        {
          "number": 7,
          "textArabic": "فَإِذَا فَرَغْتَ فَٱنصَبْ"
        },
        {
          "number": 8,
          "textArabic": "وَإِلَىٰ رَبِّكَ فَٱرْغَب"
        }
      ]
    },
    {
      "number": 95,
      "nameArabic": "التين",
      "nameTransliteration": "At-Tin",
      "nameTranslation": "The Fig",
      "ayahCount": 8,
      "revelation": "Makkah",
      "ayahs": [
        {
          "number": 1,
          "textArabic": "وَٱلتِّينِ وَٱلزَّيْتُونِ"
        },
        {
          "number": 2,
          "textArabic": "وَطُورِ سِينِينَ"
        },
        {
          "number": 3,
          "textArabic": "وَهَـٰذَا ٱلْبَلَدِ ٱلْأَمِينِ"
        },
        {
          "number": 4,
          "textArabic": "لَقَدْ خَلَقْنَا ٱلْإِنسَـٰنَ فِىٓ أَحْسَنِ تَقْوِيمٍ"
        },
        {
          "number": 5,
          "textArabic": "ثُمَّ رَدَدْنَـٰهُ أَسْفَلَ سَـٰفِلِينَ"
        },
        {
          "number": 6,
          "textArabic": "إِلَّا ٱلَّذِينَ ءَامَنُوا۟ وَعَمِلُوا۟ ٱلصَّـٰلِحَـٰتِ فَلَهُمْ أَجْرٌ غَيْرُ مَمْنُونٍ"
        },
        {
          "number": 7,
          "textArabic": "فَمَا يُكَذِّبُكَ بَعْدُ بِٱلدِّينِ"
        },
        {
          "number": 8,
          "textArabic": "أَلَيْسَ ٱللَّهُ بِأَحْكَمِ ٱلْحَـٰكِمِينَ"
        }
      ]
    },
    {
      "number": 96,
      "nameArabic": "العلق",
      "nameTransliteration": "Al-'Alaq",
      "nameTranslation": "The Clot",
      "ayahCount": 19,
      "revelation": "Makkah",
      "ayahs": [
        {
          "number": 1,
          "textArabic": " ٱقْرَأْ بِٱسْمِ رَبِّكَ ٱلَّذِى خَلَقَ"
        },
        {
          "number": 2,
          "textArabic": "خَلَقَ ٱلْإِنسَـٰنَ مِنْ عَلَقٍ"
        },
        {
          "number": 3,
          "textArabic": "ٱقْرَأْ وَرَبُّكَ ٱلْأَكْرَمُ"
        },
        {
          "number": 4,
          "textArabic": "ٱلَّذِى عَلَّمَ بِٱلْقَلَمِ"
        },
        {
          "number": 5,
          "textArabic": "عَلَّمَ ٱلْإِنسَـٰنَ مَا لَمْ يَعْلَمْ"
        },
        {
          "number": 6,
          "textArabic": "كَلَّآ إِنَّ ٱلْإِنسَـٰنَ لَيَطْغَىٰٓ"
        },
        {
          "number": 7,
          "textArabic": "أَن رَّءَاهُ ٱسْتَغْنَىٰٓ"
        },
        {
          "number": 8,
          "textArabic": "إِنَّ إِلَىٰ رَبِّكَ ٱلرُّجْعَىٰٓ"
        },
        {
          "number": 9,
          "textArabic": "أَرَءَيْتَ ٱلَّذِى يَنْهَىٰ"
        },
        {
          "number": 10,
          "textArabic": "عَبْدًا إِذَا صَلَّىٰٓ"
        },
        {
          "number": 11,
          "textArabic": "أَرَءَيْتَ إِن كَانَ عَلَى ٱلْهُدَىٰٓ"
        },
        {
          "number": 12,
          "textArabic": "أَوْ أَمَرَ بِٱلتَّقْوَىٰٓ"
        },
        {
          "number": 13,
          "textArabic": "أَرَءَيْتَ إِن كَذَّبَ وَتَوَلَّىٰٓ"
        },
        {
          "number": 14,
          "textArabic": "أَلَمْ يَعْلَم بِأَنَّ ٱللَّهَ يَرَىٰ"
        },
        {
          "number": 15,
          "textArabic": "كَلَّا لَئِن لَّمْ يَنتَهِ لَنَسْفَعًۢا بِٱلنَّاصِيَةِ"
        },
        {
          "number": 16,
          "textArabic": "نَاصِيَةٍ كَـٰذِبَةٍ خَاطِئَةٍ"
        },
        {
          "number": 17,
          "textArabic": "فَلْيَدْعُ نَادِيَهُۥ"
        },
        {
          "number": 18,
          "textArabic": "سَنَدْعُ ٱلزَّبَانِيَةَ"
        },
        {
          "number": 19,
          "textArabic": "كَلَّا لَا تُطِعْهُ وَٱسْجُدْ وَٱقْتَرِب ۩"
        }
      ]
    },
    {
      "number": 97,
      "nameArabic": "القدر",
      "nameTransliteration": "Al-Qadar",
      "nameTranslation": "The Night of Decree",
      "ayahCount": 5,
      "revelation": "Makkah",
      "ayahs": [
        {
          "number": 1,
          "textArabic": "إِنَّآ أَنزَلْنَـٰهُ فِى لَيْلَةِ ٱلْقَدْرِ"
        },
        {
          "number": 2,
          "textArabic": "وَمَآ أَدْرَىٰكَ مَا لَيْلَةُ ٱلْقَدْرِ"
        },
        {
          "number": 3,
          "textArabic": "لَيْلَةُ ٱلْقَدْرِ خَيْرٌ مِّنْ أَلْفِ شَهْرٍ"
        },
        {
          "number": 4,
          "textArabic": "تَنَزَّلُ ٱلْمَلَـٰٓئِكَةُ وَٱلرُّوحُ فِيهَا بِإِذْنِ رَبِّهِم مِّن كُلِّ أَمْرٍ"
        },
        {
          "number": 5,
          "textArabic": "سَلَـٰمٌ هِىَ حَتَّىٰ مَطْلَعِ ٱلْفَجْرِ"
        }
      ]
    },
    {
      "number": 98,
      "nameArabic": "البينة",
      "nameTransliteration": "Al-Bayyinah",
      "nameTranslation": "The Clear Evidence",
      "ayahCount": 8,
      "revelation": "Madinah",
      "ayahs": [
        {
          "number": 1,
          "textArabic": " لَمْ يَكُنِ ٱلَّذِينَ كَفَرُوا۟ مِنْ أَهْلِ ٱلْكِتَـٰبِ وَٱلْمُشْرِكِينَ مُنفَكِّينَ حَتَّىٰ تَأْتِيَهُمُ ٱلْبَيِّنَةُ"
        },
        {
          "number": 2,
          "textArabic": "رَسُولٌ مِّنَ ٱللَّهِ يَتْلُوا۟ صُحُفًا مُّطَهَّرَةً"
        },
        {
          "number": 3,
          "textArabic": "فِيهَا كُتُبٌ قَيِّمَةٌ"
        },
        {
          "number": 4,
          "textArabic": "وَمَا تَفَرَّقَ ٱلَّذِينَ أُوتُوا۟ ٱلْكِتَـٰبَ إِلَّا مِنۢ بَعْدِ مَا جَآءَتْهُمُ ٱلْبَيِّنَةُ"
        },
        {
          "number": 5,
          "textArabic": "وَمَآ أُمِرُوٓا۟ إِلَّا لِيَعْبُدُوا۟ ٱللَّهَ مُخْلِصِينَ لَهُ ٱلدِّينَ حُنَفَآءَ وَيُقِيمُوا۟ ٱلصَّلَوٰةَ وَيُؤْتُوا۟ ٱلزَّكَوٰةَ ۚ وَذَٰلِكَ دِينُ ٱلْقَيِّمَةِ"
        },
        {
          "number": 6,
          "textArabic": "إِنَّ ٱلَّذِينَ كَفَرُوا۟ مِنْ أَهْلِ ٱلْكِتَـٰبِ وَٱلْمُشْرِكِينَ فِى نَارِ جَهَنَّمَ خَـٰلِدِينَ فِيهَآ ۚ أُو۟لَـٰٓئِكَ هُمْ شَرُّ ٱلْبَرِيَّةِ"
        },
        {
          "number": 7,
          "textArabic": "إِنَّ ٱلَّذِينَ ءَامَنُوا۟ وَعَمِلُوا۟ ٱلصَّـٰلِحَـٰتِ أُو۟لَـٰٓئِكَ هُمْ خَيْرُ ٱلْبَرِيَّةِ"
        },
        {
          "number": 8,
          "textArabic": "جَزَآؤُهُمْ عِندَ رَبِّهِمْ جَنَّـٰتُ عَدْنٍ تَجْرِى مِن تَحْتِهَا ٱلْأَنْهَـٰرُ خَـٰلِدِينَ فِيهَآ أَبَدًا ۖ رَّضِىَ ٱللَّهُ عَنْهُمْ وَرَضُوا۟ عَنْهُ ۚ ذَٰلِكَ لِمَنْ خَشِىَ رَبَّهُۥ"
        }
      ]
    },
    {
      "number": 99,
      "nameArabic": "الزلزلة",
      "nameTransliteration": "Az-Zalzalah",
      "nameTranslation": "The Earthquake",
      "ayahCount": 8,
      "revelation": "Madinah",
      "ayahs": [
        {
          "number": 1,
          "textArabic": " إِذَا زُلْزِلَتِ ٱلْأَرْضُ زِلْزَالَهَا"
        },
        {
          "number": 2,
          "textArabic": "وَأَخْرَجَتِ ٱلْأَرْضُ أَثْقَالَهَا"
        },
        {
          "number": 3,
          "textArabic": "وَقَالَ ٱلْإِنسَـٰنُ مَا لَهَا"
        },
        {
          "number": 4,
          "textArabic": "يَوْمَئِذٍ تُحَدِّثُ أَخْبَارَهَا"
        },
        {
          "number": 5,
          "textArabic": "بِأَنَّ رَبَّكَ أَوْحَىٰ لَهَا"
        },
        {
          "number": 6,
          "textArabic": "يَوْمَئِذٍ يَصْدُرُ ٱلنَّاسُ أَشْتَاتًا لِّيُرَوْا۟ أَعْمَـٰلَهُمْ"
        },
        {
          "number": 7,
          "textArabic": "فَمَن يَعْمَلْ مِثْقَالَ ذَرَّةٍ خَيْرًا يَرَهُۥ"
        },
        {
          "number": 8,
          "textArabic": "وَمَن يَعْمَلْ مِثْقَالَ ذَرَّةٍ شَرًّا يَرَهُۥ"
        }
      ]
    },
    {
      "number": 100,
      "nameArabic": "العاديات",
      "nameTransliteration": "Al-'Adiyat",
      "nameTranslation": "The Courser",
      "ayahCount": 11,
      "revelation": "Makkah",
      "ayahs": [
        {
          "number": 1,
          "textArabic": " وَٱلْعَـٰدِيَـٰتِ ضَبْحًا"
        },
        {
          "number": 2,
          "textArabic": "فَٱلْمُورِيَـٰتِ قَدْحًا"
        },
        {
          "number": 3,
          "textArabic": "فَٱلْمُغِيرَٰتِ صُبْحًا"
        },
        {
          "number": 4,
          "textArabic": "فَأَثَرْنَ بِهِۦ نَقْعًا"
        },
        {
          "number": 5,
          "textArabic": "فَوَسَطْنَ بِهِۦ جَمْعًا"
        },
        {
          "number": 6,
          "textArabic": "إِنَّ ٱلْإِنسَـٰنَ لِرَبِّهِۦ لَكَنُودٌ"
        },
        {
          "number": 7,
          "textArabic": "وَإِنَّهُۥ عَلَىٰ ذَٰلِكَ لَشَهِيدٌ"
        },
        {
          "number": 8,
          "textArabic": "وَإِنَّهُۥ لِحُبِّ ٱلْخَيْرِ لَشَدِيدٌ"
        },
        {
          "number": 9,
          "textArabic": "۞ أَفَلَا يَعْلَمُ إِذَا بُعْثِرَ مَا فِى ٱلْقُبُورِ"
        },
        {
          "number": 10,
          "textArabic": "وَحُصِّلَ مَا فِى ٱلصُّدُورِ"
        },
        {
          "number": 11,
          "textArabic": "إِنَّ رَبَّهُم بِهِمْ يَوْمَئِذٍ لَّخَبِيرٌۢ"
        }
      ]
    },
    {
      "number": 101,
      "nameArabic": "القارعة",
      "nameTransliteration": "Al-Qari'ah",
      "nameTranslation": "The Striking Hour",
      "ayahCount": 11,
      "revelation": "Makkah",
      "ayahs": [
        {
          "number": 1,
          "textArabic": " ٱلْقَارِعَةُ"
        },
        {
          "number": 2,
          "textArabic": "مَا ٱلْقَارِعَةُ"
        },
        {
          "number": 3,
          "textArabic": "وَمَآ أَدْرَىٰكَ مَا ٱلْقَارِعَةُ"
        },
        {
          "number": 4,
          "textArabic": "يَوْمَ يَكُونُ ٱلنَّاسُ كَٱلْفَرَاشِ ٱلْمَبْثُوثِ"
        },
        {
          "number": 5,
          "textArabic": "وَتَكُونُ ٱلْجِبَالُ كَٱلْعِهْنِ ٱلْمَنفُوشِ"
        },
        {
          "number": 6,
          "textArabic": "فَأَمَّا مَن ثَقُلَتْ مَوَٰزِينُهُۥ"
        },
        {
          "number": 7,
          "textArabic": "فَهُوَ فِى عِيشَةٍ رَّاضِيَةٍ"
        },
        {
          "number": 8,
          "textArabic": "وَأَمَّا مَنْ خَفَّتْ مَوَٰزِينُهُۥ"
        },
        {
          "number": 9,
          "textArabic": "فَأُمُّهُۥ هَاوِيَةٌ"
        },
        {
          "number": 10,
          "textArabic": "وَمَآ أَدْرَىٰكَ مَا هِيَهْ"
        },
        {
          "number": 11,
          "textArabic": "نَارٌ حَامِيَةٌۢ"
        }
      ]
    },
    {
      "number": 102,
      "nameArabic": "التكاثر",
      "nameTransliteration": "At-Takathur",
      "nameTranslation": "The Rivalry",
      "ayahCount": 8,
      "revelation": "Makkah",
      "ayahs": [
        {
          "number": 1,
          "textArabic": " أَلْهَىٰكُمُ ٱلتَّكَاثُرُ"
        },
        {
          "number": 2,
          "textArabic": "حَتَّىٰ زُرْتُمُ ٱلْمَقَابِرَ"
        },
        {
          "number": 3,
          "textArabic": "كَلَّا سَوْفَ تَعْلَمُونَ"
        },
        {
          "number": 4,
          "textArabic": "ثُمَّ كَلَّا سَوْفَ تَعْلَمُونَ"
        },
        {
          "number": 5,
          "textArabic": "كَلَّا لَوْ تَعْلَمُونَ عِلْمَ ٱلْيَقِينِ"
        },
        {
          "number": 6,
          "textArabic": "لَتَرَوُنَّ ٱلْجَحِيمَ"
        },
        {
          "number": 7,
          "textArabic": "ثُمَّ لَتَرَوُنَّهَا عَيْنَ ٱلْيَقِينِ"
        },
        {
          "number": 8,
          "textArabic": "ثُمَّ لَتُسْـَٔلُنَّ يَوْمَئِذٍ عَنِ ٱلنَّعِيمِ"
        }
      ]
    },
    {
      "number": 103,
      "nameArabic": "العصر",
      "nameTransliteration": "Al-'Asr",
      "nameTranslation": "The Time",
      "ayahCount": 3,
      "revelation": "Makkah",
      "ayahs": [
        {
          "number": 1,
          "textArabic": " وَٱلْعَصْرِ"
        },
        {
          "number": 2,
          "textArabic": "إِنَّ ٱلْإِنسَـٰنَ لَفِى خُسْرٍ"
        },
        {
          "number": 3,
          "textArabic": "إِلَّا ٱلَّذِينَ ءَامَنُوا۟ وَعَمِلُوا۟ ٱلصَّـٰلِحَـٰتِ وَتَوَاصَوْا۟ بِٱلْحَقِّ وَتَوَاصَوْا۟ بِٱلصَّبْرِ"
        }
      ]
    },
    {
      "number": 104,
      "nameArabic": "الهمزة",
      "nameTransliteration": "Al-Humazah",
      "nameTranslation": "The Slanderer",
      "ayahCount": 9,
      "revelation": "Makkah",
      "ayahs": [
        {
          "number": 1,
          "textArabic": " وَيْلٌ لِّكُلِّ هُمَزَةٍ لُّمَزَةٍ"
        },
        {
          "number": 2,
          "textArabic": "ٱلَّذِى جَمَعَ مَالًا وَعَدَّدَهُۥ"
        },
        {
          "number": 3,
          "textArabic": "يَحْسَبُ أَنَّ مَالَهُۥٓ أَخْلَدَهُۥ"
        },
        {
          "number": 4,
          "textArabic": "كَلَّا ۖ لَيُنۢبَذَنَّ فِى ٱلْحُطَمَةِ"
        },
        {
          "number": 5,
          "textArabic": "وَمَآ أَدْرَىٰكَ مَا ٱلْحُطَمَةُ"
        },
        {
          "number": 6,
          "textArabic": "نَارُ ٱللَّهِ ٱلْمُوقَدَةُ"
        },
        {
          "number": 7,
          "textArabic": "ٱلَّتِى تَطَّلِعُ عَلَى ٱلْأَفْـِٔدَةِ"
        },
        {
          "number": 8,
          "textArabic": "إِنَّهَا عَلَيْهِم مُّؤْصَدَةٌ"
        },
        {
          "number": 9,
          "textArabic": "فِى عَمَدٍ مُّمَدَّدَةٍۭ"
        }
      ]
    },
    {
      "number": 105,
      "nameArabic": "الفيل",
      "nameTransliteration": "Al-Fil",
      "nameTranslation": "The Elephant",
      "ayahCount": 5,
      "revelation": "Makkah",
      "ayahs": [
        {
          "number": 1,
          "textArabic": " أَلَمْ تَرَ كَيْفَ فَعَلَ رَبُّكَ بِأَصْحَـٰبِ ٱلْفِيلِ"
        },
        {
          "number": 2,
          "textArabic": "أَلَمْ يَجْعَلْ كَيْدَهُمْ فِى تَضْلِيلٍ"
        },
        {
          "number": 3,
          "textArabic": "وَأَرْسَلَ عَلَيْهِمْ طَيْرًا أَبَابِيلَ"
        },
        {
          "number": 4,
          "textArabic": "تَرْمِيهِم بِحِجَارَةٍ مِّن سِجِّيلٍ"
        },
        {
          "number": 5,
          "textArabic": "فَجَعَلَهُمْ كَعَصْفٍ مَّأْكُولٍۭ"
        }
      ]
    },
    {
      "number": 106,
      "nameArabic": "قريش",
      "nameTransliteration": "Quraysh",
      "nameTranslation": "Quraysh",
      "ayahCount": 4,
      "revelation": "Makkah",
      "ayahs": [
        {
          "number": 1,
          "textArabic": " لِإِيلَـٰفِ قُرَيْشٍ"
        },
        {
          "number": 2,
          "textArabic": "إِۦلَـٰفِهِمْ رِحْلَةَ ٱلشِّتَآءِ وَٱلصَّيْفِ"
        },
        {
          "number": 3,
          "textArabic": "فَلْيَعْبُدُوا۟ رَبَّ هَـٰذَا ٱلْبَيْتِ"
        },
        {
          "number": 4,
          "textArabic": "ٱلَّذِىٓ أَطْعَمَهُم مِّن جُوعٍ وَءَامَنَهُم مِّنْ خَوْفٍۭ"
        }
      ]
    },
    {
      "number": 107,
      "nameArabic": "الماعون",
      "nameTransliteration": "Al-Ma'un",
      "nameTranslation": "The Small Kindnesses",
      "ayahCount": 7,
      "revelation": "Makkah",
      "ayahs": [
        {
          "number": 1,
          "textArabic": " أَرَءَيْتَ ٱلَّذِى يُكَذِّبُ بِٱلدِّينِ"
        },
        {
          "number": 2,
          "textArabic": "فَذَٰلِكَ ٱلَّذِى يَدُعُّ ٱلْيَتِيمَ"
        },
        {
          "number": 3,
          "textArabic": "وَلَا يَحُضُّ عَلَىٰ طَعَامِ ٱلْمِسْكِينِ"
        },
        {
          "number": 4,
          "textArabic": "فَوَيْلٌ لِّلْمُصَلِّينَ"
        },
        {
          "number": 5,
          "textArabic": "ٱلَّذِينَ هُمْ عَن صَلَاتِهِمْ سَاهُونَ"
        },
        {
          "number": 6,
          "textArabic": "ٱلَّذِينَ هُمْ يُرَآءُونَ"
        },
        {
          "number": 7,
          "textArabic": "وَيَمْنَعُونَ ٱلْمَاعُونَ"
        }
      ]
    },
    {
      "number": 108,
      "nameArabic": "الكوثر",
      "nameTransliteration": "Al-Kawthar",
      "nameTranslation": "The Abundance",
      "ayahCount": 3,
      "revelation": "Makkah",
      "ayahs": [
        {
          "number": 1,
          "textArabic": " إِنَّآ أَعْطَيْنَـٰكَ ٱلْكَوْثَرَ"
        },
        {
          "number": 2,
          "textArabic": "فَصَلِّ لِرَبِّكَ وَٱنْحَرْ"
        },
        {
          "number": 3,
          "textArabic": "إِنَّ شَانِئَكَ هُوَ ٱلْأَبْتَرُ"
        }
      ]
    },
    {
      "number": 109,
      "nameArabic": "الكافرون",
      "nameTransliteration": "Al-Kafirun",
      "nameTranslation": "The Disbelievers",
      "ayahCount": 6,
      "revelation": "Makkah",
      "ayahs": [
        {
          "number": 1,
          "textArabic": " قُلْ يَـٰٓأَيُّهَا ٱلْكَـٰفِرُونَ"
        },
        {
          "number": 2,
          "textArabic": "لَآ أَعْبُدُ مَا تَعْبُدُونَ"
        },
        {
          "number": 3,
          "textArabic": "وَلَآ أَنتُمْ عَـٰبِدُونَ مَآ أَعْبُدُ"
        },
        {
          "number": 4,
          "textArabic": "وَلَآ أَنَا۠ عَابِدٌ مَّا عَبَدتُّمْ"
        },
        {
          "number": 5,
          "textArabic": "وَلَآ أَنتُمْ عَـٰبِدُونَ مَآ أَعْبُدُ"
        },
        {
          "number": 6,
          "textArabic": "لَكُمْ دِينُكُمْ وَلِىَ دِينِ"
        }
      ]
    },
    {
      "number": 110,
      "nameArabic": "النصر",
      "nameTransliteration": "An-Nasr",
      "nameTranslation": "The Help",
      "ayahCount": 3,
      "revelation": "Madinah",
      "ayahs": [
        {
          "number": 1,
          "textArabic": " إِذَا جَآءَ نَصْرُ ٱللَّهِ وَٱلْفَتْحُ"
        },
        {
          "number": 2,
          "textArabic": "وَرَأَيْتَ ٱلنَّاسَ يَدْخُلُونَ فِى دِينِ ٱللَّهِ أَفْوَاجًا"
        },
        {
          "number": 3,
          "textArabic": "فَسَبِّحْ بِحَمْدِ رَبِّكَ وَٱسْتَغْفِرْهُ ۚ إِنَّهُۥ كَانَ تَوَّابًۢا"
        }
      ]
    },
    {
      "number": 111,
      "nameArabic": "المسد",
      "nameTransliteration": "Al-Masad",
      "nameTranslation": "The Palm Fiber",
      "ayahCount": 5,
      "revelation": "Makkah",
      "ayahs": [
        {
          "number": 1,
          "textArabic": " تَبَّتْ يَدَآ أَبِى لَهَبٍ وَتَبَّ"
        },
        {
          "number": 2,
          "textArabic": "مَآ أَغْنَىٰ عَنْهُ مَالُهُۥ وَمَا كَسَبَ"
        },
        {
          "number": 3,
          "textArabic": "سَيَصْلَىٰ نَارًا ذَاتَ لَهَبٍ"
        },
        {
          "number": 4,
          "textArabic": "وَٱمْرَأَتُهُۥ حَمَّالَةَ ٱلْحَطَبِ"
        },
        {
          "number": 5,
          "textArabic": "فِى جِيدِهَا حَبْلٌ مِّن مَّسَدٍۭ"
        }
      ]
    },
    {
      "number": 112,
      "nameArabic": "الإخلاص",
      "nameTransliteration": "Al-Ikhlas",
      "nameTranslation": "The Sincerity",
      "ayahCount": 4,
      "revelation": "Makkah",
      "ayahs": [
        {
          "number": 1,
          "textArabic": " قُلْ هُوَ ٱللَّهُ أَحَدٌ"
        },
        {
          "number": 2,
          "textArabic": "ٱللَّهُ ٱلصَّمَدُ"
        },
        {
          "number": 3,
          "textArabic": "لَمْ يَلِدْ وَلَمْ يُولَدْ"
        },
        {
          "number": 4,
          "textArabic": "وَلَمْ يَكُن لَّهُۥ كُفُوًا أَحَدٌۢ"
        }
      ]
    },
    {
      "number": 113,
      "nameArabic": "الفلق",
      "nameTransliteration": "Al-Falaq",
      "nameTranslation": "The Daybreak",
      "ayahCount": 5,
      "revelation": "Makkah",
      "ayahs": [
        {
          "number": 1,
          "textArabic": " قُلْ أَعُوذُ بِرَبِّ ٱلْفَلَقِ"
        },
        {
          "number": 2,
          "textArabic": "مِن شَرِّ مَا خَلَقَ"
        },
        {
          "number": 3,
          "textArabic": "وَمِن شَرِّ غَاسِقٍ إِذَا وَقَبَ"
        },
        {
          "number": 4,
          "textArabic": "وَمِن شَرِّ ٱلنَّفَّـٰثَـٰتِ فِى ٱلْعُقَدِ"
        },
        {
          "number": 5,
          "textArabic": "وَمِن شَرِّ حَاسِدٍ إِذَا حَسَدَ"
        }
      ]
    },
    {
      "number": 114,
      "nameArabic": "الناس",
      "nameTransliteration": "An-Nas",
      "nameTranslation": "Mankind",
      "ayahCount": 6,
      "revelation": "Makkah",
      "ayahs": [
        {
          "number": 1,
          "textArabic": " قُلْ أَعُوذُ بِرَبِّ ٱلنَّاسِ"
        },
        {
          "number": 2,
          "textArabic": "مَلِكِ ٱلنَّاسِ"
        },
        {
          "number": 3,
          "textArabic": "إِلَـٰهِ ٱلنَّاسِ"
        },
        {
          "number": 4,
          "textArabic": "مِن شَرِّ ٱلْوَسْوَاسِ ٱلْخَنَّاسِ"
        },
        {
          "number": 5,
          "textArabic": "ٱلَّذِى يُوَسْوِسُ فِى صُدُورِ ٱلنَّاسِ"
        },
        {
          "number": 6,
          "textArabic": "مِنَ ٱلْجِنَّةِ وَٱلنَّاسِ"
        }
      ]
    }
  ]
}